runner_pjpawel/__init__.py
runner_pjpawel/counter.py
runner_pjpawel/progress_bar.py
runner_pjpawel/runner.py
runner_pjpawel/command/__init__.py
runner_pjpawel/command/base.py
runner_pjpawel/command/common.py
runner_pjpawel-0.1.3.dist-info/METADATA
runner_pjpawel-0.1.3.dist-info/WHEEL
runner_pjpawel-0.1.3.dist-info/licenses/LICENSE
runner_pjpawel-0.1.3.dist-info/RECORD
