Metadata-Version: 2.4
Name: runner-pjpawel
Version: 0.1.3
Summary: Universal runner with builder objects to run async, threaded or group commands
Project-URL: Homepage, https://github.com/pjpawel/runner
Project-URL: Issues, https://github.com/pjpawel/runner/issues
Author-email: pjpawel <pjpawel@proton.me>
License-Expression: Apache-2.0
License-File: LICENSE
Classifier: Development Status :: 3 - Alpha
Classifier: Operating System :: OS Independent
Classifier: Programming Language :: Python :: 3
Requires-Python: >=3.9
